origo/lambda_helpers/__init__.py
origo/lambda_helpers/logging.py
origo_lambda_helpers-0.1.0.dist-info/METADATA
origo_lambda_helpers-0.1.0.dist-info/WHEEL
origo_lambda_helpers-0.1.0.dist-info/top_level.txt
origo_lambda_helpers-0.1.0.dist-info/RECORD
