Metadata-Version: 2.1
Name: origo-lambda-helpers
Version: 0.1.0
Summary: SDK for origo
Home-page: https://github.com/oslokommune/origo-lambda-helpers-python
Author: Oslo Origo
Author-email: dataplattform@oslo.kommune.no
License: UNKNOWN
Platform: UNKNOWN
Classifier: Development Status :: 3 - Alpha
Classifier: Programming Language :: Python :: 3
Classifier: License :: OSI Approved :: MIT License
Classifier: Operating System :: OS Independent
Requires-Python: >=3.6
Requires-Dist: structlog
